.coveragerc
.gitignore
.readthedocs.yaml
CHANGELOG.rst
LICENSE
README.md
pyproject.toml
.github/workflows/run_test.yml
docs/Makefile
docs/citing.rst
docs/conf.py
docs/index.rst
docs/invariants.rst
docs/make.bat
docs/methodology.rst
docs/models.rst
docs/rbinvariantslib.rst
docs/_static/driftshell.png
docs/_static/logo.png
docs/_static/logo.svg
docs/_static/poster.pdf
docs/_templates/github.html
docs/_templates/logo.html
docs/_templates/styles.css
docs/whatsnew/changelog.rst
docs/whatsnew/index.rst
rbinvariantslib/__init__.py
rbinvariantslib/_version.py
rbinvariantslib/constants.py
rbinvariantslib/invariants.py
rbinvariantslib/models.py
rbinvariantslib/utils.py
rbinvariantslib.egg-info/PKG-INFO
rbinvariantslib.egg-info/SOURCES.txt
rbinvariantslib.egg-info/dependency_links.txt
rbinvariantslib.egg-info/requires.txt
rbinvariantslib.egg-info/top_level.txt
rbinvariantslib/tests/test_examples.py
rbinvariantslib/tests/test_invariants.py
rbinvariantslib/tests/test_models.py
rbinvariantslib/tests/test_tsyganenko_cdaweb.py
rbinvariantslib/tests/testing_utils.py