Metadata-Version: 2.4
Name: rbinvariantslib
Version: 0.3.0
Summary: Radiation Belt Adiabatic Invariants Calculation from TS05, T96, LFM, and SWMF magnetic field models
Author-email: Daniel da Silva <daniel.e.dasilva@nasa.gov>
License: Copyright (c) 2024, Daniel da Silva
Project-URL: Homepage, https://rbinvariantslib.readthedocs.io/en/latest/
Classifier: Development Status :: 4 - Beta
Classifier: Intended Audience :: Science/Research
Classifier: Programming Language :: Python :: 3.8
Classifier: Programming Language :: Python :: 3.9
Classifier: Programming Language :: Python :: 3.10
Classifier: Programming Language :: Python :: 3.11
Classifier: Programming Language :: Python :: 3.12
Classifier: License :: OSI Approved :: BSD License
Requires-Python: >=3.8
License-File: LICENSE
Requires-Dist: astropy>=5.1
Requires-Dist: cdasws>=1.8.7
Requires-Dist: h5py>=3.10.0
Requires-Dist: numpy<2,>=1.24.4
Requires-Dist: PyGeopack>=1.2.6
Requires-Dist: pyhdf
Requires-Dist: pyvista
Requires-Dist: scipy>=1.9.3
Requires-Dist: spacepy>=0.7.0
Requires-Dist: types-python-dateutil
Provides-Extra: dev
Requires-Dist: coverage; extra == "dev"
Requires-Dist: pytest; extra == "dev"
Requires-Dist: requests; extra == "dev"
Provides-Extra: docs
Requires-Dist: sphinx; extra == "docs"
Requires-Dist: sphinx_automodapi; extra == "docs"
Requires-Dist: numpydoc; extra == "docs"
Requires-Dist: pydata_sphinx_theme; extra == "docs"
Requires-Dist: furo; extra == "docs"
Dynamic: license-file
